nirpy
