Metadata-Version: 1.0
Name: nirpy
Version: 1.0.2
Summary: Use nircmdc commands in python
Home-page: https://github.com/LimerBoy/nirpy
Author: LimerBoy
Author-email: LimerBoyTV@gmail.com
License: MIT
Platform: UNKNOWN
